cellColor/__init__.py
cellColor/_opencv_config.py
cellColor/gui.py
cellColor/main.py
cellColor/image_utils/__init__.py
cellColor/image_utils/image_loader.py
cellColor/image_utils/zoom.py
cellColor/overlays/__init__.py
cellColor/overlays/cell_centers.py
cellColor/overlays/cellpose_loader.py
cellColor/overlays/colors.py
cellColor/overlays/genes.py
cellcolor-0.2.3.dist-info/licenses/LICENSE
cellcolor-0.2.3.dist-info/METADATA
cellcolor-0.2.3.dist-info/WHEEL
cellcolor-0.2.3.dist-info/entry_points.txt
cellcolor-0.2.3.dist-info/top_level.txt
cellcolor-0.2.3.dist-info/RECORD
