Metadata-Version: 2.4
Name: cellColor
Version: 0.2.3
Summary: An app for exploring spatial transcriptomics and cell segmentations by overlaying data
Author-email: Anthea Guo <anthea.jin.guo@gmail.com>
License-Expression: MIT
Project-URL: Homepage, https://github.com/crocodile27/cellColor
Keywords: spatial-transcriptomics,cell-segmentation,visualization,microscopy,cellpose,bioinformatics
Classifier: Development Status :: 4 - Beta
Classifier: Intended Audience :: Science/Research
Classifier: Programming Language :: Python :: 3
Classifier: Programming Language :: Python :: 3.9
Classifier: Programming Language :: Python :: 3.10
Classifier: Programming Language :: Python :: 3.11
Classifier: Topic :: Scientific/Engineering :: Bio-Informatics
Classifier: Topic :: Scientific/Engineering :: Visualization
Requires-Python: >=3.9
License-File: LICENSE
Requires-Dist: numpy<2.0.0,>=1.20.0
Requires-Dist: pandas>=1.3.0
Requires-Dist: anndata>=0.8.0
Requires-Dist: qtpy>=2.0.0
Requires-Dist: PyQt5>=5.15.0
Requires-Dist: opencv-python>=4.5.0
Requires-Dist: cellpose>=2.0.0
Requires-Dist: pyarrow>=10.0.0
Dynamic: license-file
